{
    "text":  "ncremento no Valor deHabilidade 3 3 – – – –\n5° +3 Característica deConclave dePatrulheiro 4 4 2 – – –\n6° +3 InimigoFavoritoMaior 4 4 2 – – –\n7° +3 Característica deConclave dePatrulheiro 5 4 3 – – –\n8° +3 Incremento no Valor deHabilidade,PésRápidos 5 4 3 – – –\n9° +4 – 6 4 3 2 – –\n10° +4 Mimetismo 6 4 3 2 – –\n11° +4 Característica deConclave dePatrulheiro 7 4 3 3 – –\n12° +4 Incremento no Valor deHabilidade 7 4 3 3 – –\n13° +5 – 8 4 3 3 1 –\n14° +5 Desaparecer 8 4 3 3 1 –\n15° +5 Característica deConclave dePatrulheiro 9 4 3 3 2 –\n16° +5 Incremento no Valor deHabilidade 9 4 3 3 2 –\n17° +6 – 10 4 3 3 3 1\n18° +6 SentidosSelvagens 10 4 3 3 3 1\n19° +6 Incremento no Valor deHabilidade 11 4 3 3 3 2\n20° +6 Matador deInimigos 11 4 3 3 3 2\nQual afontedoseu ódioparticular por umcertotipo\ndeinimigo? Ummonstromatou alguémquevocêamava\nou destruiu suavilanatal?Ouvocêviumuitada\ndestruiçãocausadapor essesmonstroseseimpeliu a\nacabarcomsuasdepredações? Suacarreira como\naventureiroéumacontinuaçãodoseu trabalhoem\nproteger asfronteiras, ouumamudançasignificativa?O\nEssa independência feroz faz dospatrulheirosótimos quefez vocêsejuntar aumbandodeaventureiros? Você\naventureiros, jáqueelessãoacostumadosavida longedo achouqueseria desafiador ensinar novosaliadosos\nconfortodeumacamaseca ebanhoquente. Confrontado caminhosdanatureza, ouvocêaprecioualibertaçãoda\ncom aventureirosmaisurbanosquereclamame solidãoqueelesofereceram?\nchoramingamsobreadurezadavidanoambiente\nselvagem, ospatrulheirosrespondemcomumamisturade CONSTRUÇÃORÁPIDA\ndivertimento, frustraçãoecompaixão. Mas, eles Vocêpodeconstruir umpatrulheirorapidamente\nrapidamenteaprendemqueosoutrosaventureirosque seguindoessassugestões. Primeiro, coloqueseuvalor de\npodemcarregar seusprópriosfardosemumaluta contra habilidademaisaltoemDestreza, seguidodeSabedoria.\nosinimigosdacivilizaçãosãodignosdequalquer encargo (Algunspatrulheirosquesefocamnocombatecomduas\nadicional.Gentemimadadacidadepodemnãosaber como armasdeixamaForça maior queaDestreza.) Segundo",
    "metadata":  {
                     "total_chunks":  653,
                     "language":  "pt-BR",
                     "game_system":  "dnd5e",
                     "source_file":  "dd-5e-livro-do-jogador-fundo-branco-biblioteca-elfica.pdf",
                     "chunk_index":  231,
                     "document_type":  "player_handbook",
                     "title":  "Livro do Jogador"
                 }
}
